{
   "experimentName": "EEG_Valence_Recognition_DEAP",
   "experimentType": "classification",
   "batchSize": 10,
   "csvFilePath": "/home/nerlnet/data/persons_csvs/persons_normalize_valence/1_3_persons_normalize_valence.csv",
   "numOfFeatures": "70",
   "numOfLabels": "9",
   "headersNames": "1,2,3,4,5,6,7,8,9",
   "Phases": 
   [
      {
         "phaseName": "training_phase",
         "phaseType": "training",
         "sourcePieces":
         [
            {
            "sourceName": "s1",
            "startingSample": "10",
            "numOfBatches": "400",
            "workers": "w1,w2,w3,w4",
            "nerltensorType": "float"
            }
         ]  
      },
      {
         "phaseName": "prediction_phase",
         "phaseType": "prediction",
         "sourcePieces":
         [
            {
            "sourceName": "s1",
            "startingSample": "16510",
            "numOfBatches": "100",
            "workers": "w1,w2,w3,w4",
            "nerltensorType": "float"
            }
         ]    
      }
   ]
}
    
